LICENCE
MANIFEST.in
README.rst
readthedocs.txt
requirements.txt
setup.py
mob/__init__.py
mob/middleware.py
mob/models.py
mob/tests.py
mob/urls.py
mob/views.py
mob.egg-info/PKG-INFO
mob.egg-info/SOURCES.txt
mob.egg-info/dependency_links.txt
mob.egg-info/top_level.txt
tests/app/__init__.py
tests/app/models.py
tests/app/tests.py
tests/app/user_agents.py
tests/app/views.py