Metadata-Version: 1.0
Name: mob
Version: 0.0.1
Summary: UNKNOWN
Home-page: https://github.com/caffeinehit/django-mob
Author: Alen Mujezinovic
Author-email: alen@caffeinehit.com
License: Copyright (c) 2012, Caffeinehit Ltd.
